{
	"configurations" : 
	[
		{
			"directories" : 
			[
				{
					"build" : ".",
					"childIndexes" : 
					[
						1
					],
					"jsonFile" : "directory-.-Debug-d0094a50bb2071803777.json",
					"minimumCMakeVersion" : 
					{
						"string" : "3.16"
					},
					"projectIndex" : 0,
					"source" : ".",
					"targetIndexes" : 
					[
						0,
						1
					]
				},
				{
					"build" : "qcustomplot",
					"jsonFile" : "directory-qcustomplot-Debug-579a435c04da251a2c17.json",
					"minimumCMakeVersion" : 
					{
						"string" : "3.16"
					},
					"parentIndex" : 0,
					"projectIndex" : 1,
					"source" : "qcustomplot",
					"targetIndexes" : 
					[
						2,
						3
					]
				}
			],
			"name" : "Debug",
			"projects" : 
			[
				{
					"childIndexes" : 
					[
						1
					],
					"directoryIndexes" : 
					[
						0
					],
					"name" : "ProtosLogViewer",
					"targetIndexes" : 
					[
						0,
						1
					]
				},
				{
					"directoryIndexes" : 
					[
						1
					],
					"name" : "qcustomplot",
					"parentIndex" : 0,
					"targetIndexes" : 
					[
						2,
						3
					]
				}
			],
			"targets" : 
			[
				{
					"directoryIndex" : 0,
					"id" : "ProtosLogViewer::@6890427a1f51a3e7e1df",
					"jsonFile" : "target-ProtosLogViewer-Debug-ff4c33f67b06c002dbc1.json",
					"name" : "ProtosLogViewer",
					"projectIndex" : 0
				},
				{
					"directoryIndex" : 0,
					"id" : "ProtosLogViewer_autogen::@6890427a1f51a3e7e1df",
					"jsonFile" : "target-ProtosLogViewer_autogen-Debug-b0caf363bbb7d1a16d0e.json",
					"name" : "ProtosLogViewer_autogen",
					"projectIndex" : 0
				},
				{
					"directoryIndex" : 1,
					"id" : "qcustomplot::@82c41707adc1c3375302",
					"jsonFile" : "target-qcustomplot-Debug-64bea0c98e0eca970664.json",
					"name" : "qcustomplot",
					"projectIndex" : 1
				},
				{
					"directoryIndex" : 1,
					"id" : "qcustomplot_autogen::@82c41707adc1c3375302",
					"jsonFile" : "target-qcustomplot_autogen-Debug-de55fbbb40ff50cc35d1.json",
					"name" : "qcustomplot_autogen",
					"projectIndex" : 1
				}
			]
		}
	],
	"kind" : "codemodel",
	"paths" : 
	{
		"build" : "C:/Users/user/CLionProjects/ProtosLogViewer/build-ProtosLogViewer-Desktop-Debug",
		"source" : "C:/Users/user/CLionProjects/ProtosLogViewer"
	},
	"version" : 
	{
		"major" : 2,
		"minor" : 4
	}
}
